dbgone/__init__.py
dbgone/config/__init__.py
dbgone/config/main.py
dbgone/llm/__init__.py
dbgone/llm/llm.py
dbgone/llm/prompts/__init__.py
dbgone/llm/prompts/analysis_prompt_creator.py
dbgone/llm/prompts/base.py
dbgone/opt/__init__.py
dbgone/opt/manager.py
dbgone/opt/params.py
dbgone/torch/__init__.py
dbgone/torch/manager.py
dbgone-0.0.1a9.dist-info/LICENSE
dbgone-0.0.1a9.dist-info/METADATA
dbgone-0.0.1a9.dist-info/WHEEL
dbgone-0.0.1a9.dist-info/top_level.txt
dbgone-0.0.1a9.dist-info/RECORD
