Metadata-Version: 2.1
Name: dbgone
Version: 0.0.1a9
Summary: A common library frequently used on python
Home-page: https://github.com/Viyyy/dbgone
Author: Re.VI
Author-email: another91026@gmail.com
License: Apache License 2.0
License-File: LICENSE
Requires-Dist: optuna
Requires-Dist: pydantic
Requires-Dist: python-dotenv
Requires-Dist: langchain
Requires-Dist: langchain[openai]
Requires-Dist: langchain[community]
Provides-Extra: torch
Requires-Dist: torch ; extra == 'torch'
